.coveragerc
.gitattributes
.gitignore
.pep8speaks.yml
.travis.yml
CHANGELOG.md
LICENSE
MANIFEST.in
Makefile
README.md
example-conf.yaml
requirements-test.txt
requirements.txt
setup.cfg
setup.py
conda_mirror_ng/__init__.py
conda_mirror_ng/conda_mirror.py
conda_mirror_ng.egg-info/PKG-INFO
conda_mirror_ng.egg-info/SOURCES.txt
conda_mirror_ng.egg-info/dependency_links.txt
conda_mirror_ng.egg-info/entry_points.txt
conda_mirror_ng.egg-info/requires.txt
conda_mirror_ng.egg-info/top_level.txt
test/conftest.py
test/test_conda_mirror.py