Metadata-Version: 2.1
Name: conda-mirror-ng
Version: 0.8.1
Summary: Mirror an upstream conda channel to a local directory
Home-page: https://github.com/xhochy/conda-mirror-ng
Author: Eric Dill
License: BSD 3-Clause
Platform: Linux
Platform: Mac OSX
Platform: Windows
